{
"type": "FeatureCollection",
"crs": { "type": "name", "properties": { "name": "urn:ogc:def:crs:OGC:1.3:CRS84" } },
"features": [
{ "type": "Feature", "properties": { "IDEQUIPAMENT": 55455, "ALIES": "Reial Club Marítim de Barcelona", "NOM": "Reial Club Marítim de Barcelona", "CATEGORIA": "Mobilitat. Transports|Ports esportius||", "TIPUS_VIA": "pl.", "VIA": " d' Espanya", "SUFIX_VIA": null, "NUM": "s\/n", "CPOSTAL": "08014", "POBLACIO": "Barcelona", "COMARCA": "Barcelonès", "TELEFON1": null, "TELEFON2": null, "FAX": null, "UTMX": 431770, "UTMY": 4581049, "LONGITUD": 2.182939476, "LATITUD": 41.376221752, "EMAIL": null, "WEB": null, "DATA_MODIFICACIO": "01\/31\/2018 12:59:31 PM +0000", "PROPIETATS": null, "LOCALITZACIO": null }, "geometry": { "type": "Point", "coordinates": [ 2.182939476, 41.376221752 ] } },
{ "type": "Feature", "properties": { "IDEQUIPAMENT": 55454, "ALIES": "Port Olímpic", "NOM": "Port Olímpic", "CATEGORIA": "Mobilitat. Transports|Ports esportius||", "TIPUS_VIA": null, "VIA": " Edifici Capitania", "SUFIX_VIA": null, "NUM": "s\/n", "CPOSTAL": "08005", "POBLACIO": "Barcelona", "COMARCA": "Barcelonès", "TELEFON1": null, "TELEFON2": null, "FAX": null, "UTMX": 433176, "UTMY": 4581863, "LONGITUD": 2.20083333, "LATITUD": 41.3855556, "EMAIL": null, "WEB": null, "DATA_MODIFICACIO": "01\/31\/2018 12:59:32 PM +0000", "PROPIETATS": null, "LOCALITZACIO": null }, "geometry": { "type": "Point", "coordinates": [ 2.20083333, 41.3855556 ] } },
{ "type": "Feature", "properties": { "IDEQUIPAMENT": 759372, "ALIES": "Reial Club Nàutic de Barcelona", "NOM": "Reial Club Nàutic de Barcelona", "CATEGORIA": "Mobilitat. Transports|Ports esportius||", "TIPUS_VIA": null, "VIA": " null null null", "SUFIX_VIA": null, "NUM": null, "CPOSTAL": "-", "POBLACIO": "Barcelona", "COMARCA": "Barcelonès", "TELEFON1": null, "TELEFON2": null, "FAX": null, "UTMX": 432035, "UTMY": 4581152, "LONGITUD": 2.186096645, "LATITUD": 41.377171885000003, "EMAIL": null, "WEB": null, "DATA_MODIFICACIO": "01\/31\/2018 12:59:31 PM +0000", "PROPIETATS": null, "LOCALITZACIO": null }, "geometry": { "type": "Point", "coordinates": [ 2.186096645, 41.377171885 ] } },
{ "type": "Feature", "properties": { "IDEQUIPAMENT": 759374, "ALIES": "Marina Port Vell de Barcelona", "NOM": "Marina Port Vell de Barcelona", "CATEGORIA": "Mobilitat. Transports|Ports esportius||", "TIPUS_VIA": null, "VIA": " null null null", "SUFIX_VIA": null, "NUM": null, "CPOSTAL": "-", "POBLACIO": "Barcelona", "COMARCA": "Barcelonès", "TELEFON1": null, "TELEFON2": null, "FAX": null, "UTMX": 431652, "UTMY": 4580784, "LONGITUD": 2.181558394, "LATITUD": 41.373824945000003, "EMAIL": null, "WEB": null, "DATA_MODIFICACIO": "01\/31\/2018 12:59:32 PM +0000", "PROPIETATS": null, "LOCALITZACIO": null }, "geometry": { "type": "Point", "coordinates": [ 2.181558394, 41.373824945 ] } }
]
}
